__init__.py
govdelivery/__init__.py
govdelivery/authorization.py
govdelivery/bulletins.py
govdelivery/categories.py
govdelivery/subscriptions.py
govdelivery/topics.py
gxcloud-0.1.9.dist-info/licenses/LICENSE
opencities/__init__.py
opencities/authorization.py
opencities/files.py
opencities/pages.py
utilities/__init__.py
gxcloud-0.1.9.dist-info/METADATA
gxcloud-0.1.9.dist-info/WHEEL
gxcloud-0.1.9.dist-info/top_level.txt
gxcloud-0.1.9.dist-info/RECORD
