Metadata-Version: 2.4
Name: gxcloud
Version: 0.1.9
Summary: A python package for using the OpenCities API
Author-email: Zac Thiel <zac.thiel@granicus.com>
Classifier: Programming Language :: Python :: 3
Classifier: License :: OSI Approved :: MIT License
Classifier: Operating System :: OS Independent
Requires-Python: >=3.8
License-File: LICENSE
Requires-Dist: requests
Requires-Dist: xmltodict
Dynamic: license-file
